boto_collator_client.py
boto_collator_client-0.2.0.dist-info/WHEEL
boto_collator_client-0.2.0.dist-info/METADATA
boto_collator_client-0.2.0.dist-info/RECORD
